sq_midi/__init__.py
sq_midi/channel.py
sq_midi/channel_wrapper.py
sq_midi/mixer.py
sq_midi/parameter_handler.py
sq_midi/parameter_wrapper.py
sq_midi/channels/__init__.py
sq_midi/channels/_aux.py
sq_midi/channels/dca.py
sq_midi/channels/fx_return.py
sq_midi/channels/fx_send.py
sq_midi/channels/group.py
sq_midi/channels/input.py
sq_midi/channels/lr.py
sq_midi/channels/matrix.py
sq_midi/channels/mute_groups.py
sq_midi/data/__init__.py
sq_midi/data/auxes.json
sq_midi/data/fx_returns.json
sq_midi/data/fx_sends.json
sq_midi/data/groups.json
sq_midi/data/inputs.json
sq_midi/data/loader.py
sq_midi/data/lr.json
sq_midi/data/old/SQ-MIDI-Protocol-Issue5.pdf
sq_midi/data/old/dcas.json
sq_midi/data/old/matrices.json
sq_midi/data/old/mute_groups.json
sq_midi-0.0.8.dist-info/METADATA
sq_midi-0.0.8.dist-info/WHEEL
sq_midi-0.0.8.dist-info/RECORD
