Metadata-Version: 2.4
Name: sq_midi
Version: 0.0.8
Summary: A package to control Allen & Heath SQ mixers via MIDI
Author: Philip Smith
Classifier: Operating System :: OS Independent
Classifier: Programming Language :: Python :: 3
Requires-Python: <3.13,>=3.9
Requires-Dist: mido>=1.3.3
Requires-Dist: python-rtmidi>=1.5.8
